LICENSE.txt
README.md
setup.cfg
setup.py
pythonskole/__init__.py
pythonskole/astronomi.py
pythonskole/tyngdekraft.test.py
pythonskole.egg-info/PKG-INFO
pythonskole.egg-info/SOURCES.txt
pythonskole.egg-info/dependency_links.txt
pythonskole.egg-info/requires.txt
pythonskole.egg-info/top_level.txt