Metadata-Version: 2.1
Name: pythonskole
Version: 1.0.4
Summary: Koder til bruk i undervisning i Python
Home-page: https://github.com/vegardlr/pythonskole
Download-URL: https://github.com/vegardlr/pythonskole/archive/refs/tags/v1.0.4.tar.gz
Author: Vegard Lundby Rekaa
Author-email: vegard@pythonskole.no
License: gpl-3.0
Keywords: Pythonskole,Undervisning,Koding,Python,Programmering,Læring
Classifier: Development Status :: 4 - Beta
Classifier: Intended Audience :: Education
Classifier: Topic :: Software Development :: Build Tools
Classifier: License :: OSI Approved :: GNU General Public License v3 (GPLv3)
Classifier: Programming Language :: Python :: 3
Classifier: Programming Language :: Python :: 3.4
Classifier: Programming Language :: Python :: 3.5
Classifier: Programming Language :: Python :: 3.6
Classifier: Programming Language :: Python :: 3.8
Classifier: Programming Language :: Python :: 3.9
Classifier: Programming Language :: Python :: 3.10
License-File: LICENSE.txt
